[
	{"team":"12","num":"2","score":"237"},
	{"team":"15","num":"2","score":"53"},
	{"team":"7","num":"2","score":"-71"},
	{"team":"8","num":"2","score":"-219"},
	{"team":"2","num":"2","score":"-316"},
	{"team":"4","num":"2","score":"-108"},
	{"team":"6","num":"2","score":"153"},
	{"team":"16","num":"2","score":"271"},
	{"team":"18","num":"2","score":"-313"},
	{"team":"19","num":"2","score":"-66"},
	{"team":"21","num":"2","score":"118"},
	{"team":"13","num":"2","score":"261"},
	{"team":"8","num":"4","score":"359"},
	{"team":"7","num":"4","score":"169"},
	{"team":"23","num":"4","score":"-31"},
	{"team":"22","num":"4","score":"-497"},
	{"team":"12","num":"4","score":"316"},
	{"team":"21","num":"4","score":"106"},
	{"team":"10","num":"4","score":"-159"},
	{"team":"1","num":"4","score":"-263"},
	{"team":"24","num":"2","score":"-349"},
	{"team":"14","num":"2","score":"-101"},
	{"team":"23","num":"2","score":"157"},
	{"team":"5","num":"2","score":"293"}
]
